Workbook

Sheet Payroll Register
A1: VELOCE DYNAMIC Pvt Ltd
A2: EMPLOYEE PAYROLL MANAGEMENT SYSTEM | Month: June 2025
A4: EMPLOYEE INFO | D4: ATTENDANCE & HOURS | H4: OVERTIME | K4: EARNINGS | N4: DEDUCTIONS | P4: NET PAY
A5: Emp ID | B5: Employee Name | C5: Basic Salary (PKR) | D5: Total Hours | E5: Hours Worked | F5: Absents | G5: Absent Deduction (PKR) | H5: OT Hours | I5: OT Rate (1.5x) | J5: OT Pay (PKR) | K5: Allowances (PKR) | L5: Gross Salary (PKR) | M5: EOBI (PKR) | N5: Income Tax (PKR) | O5: Net Pay (PKR)
A6: 1001 | B6: Ahmed Ali | C6: 250000 | D6: 160 | E6: 152 | F6: 1 | G6: =IF(F6=0,0,(C6/D6)*8*F6) -> 12500 | H6: 0 | I6: =C6/D6*1.5 -> 2343.75 | J6: =H6*I6 -> 0 | K6: 50000 | L6: =(C6-G6)+J6+K6 -> 287500 | M6: 400 | N6: =ROUND(IF(L6*12<=600000, 0,IF(L6*12<=1200000, (L6*12-600000)*0.05,IF(L6*12<=2400000, 30000+(L6*12-1200000)*0.15,IF(L6*12<=3600000, 210000+(L6*12-2400000)*0.25,510000+(L6*12-3600000)*0.3))))/12, 0) -> 39375 | O6: =L6-M6-N6 -> 247725
A7: 1002 | B7: Sara Khan | C7: 85000 | D7: 160 | E7: 160 | F7: 0 | G7: =IF(F7=0,0,(C7/D7)*8*F7) -> 0 | H7: 8 | I7: =C7/D7*1.5 -> 796.875 | J7: =H7*I7 -> 6375 | K7: 15000 | L7: =(C7-G7)+J7+K7 -> 106375 | M7: 400 | N7: =ROUND(IF(L7*12<=600000, 0,IF(L7*12<=1200000, (L7*12-600000)*0.05,IF(L7*12<=2400000, 30000+(L7*12-1200000)*0.15,IF(L7*12<=3600000, 210000+(L7*12-2400000)*0.25,510000+(L7*12-3600000)*0.3))))/12, 0) -> 3456 | O7: =L7-M7-N7 -> 102519
A8: 1003 | B8: Bilal Sheikh | C8: 150000 | D8: 160 | E8: 160 | F8: 0 | G8: =IF(F8=0,0,(C8/D8)*8*F8) -> 0 | H8: 12 | I8: =C8/D8*1.5 -> 1406.25 | J8: =H8*I8 -> 16875 | K8: 30000 | L8: =(C8-G8)+J8+K8 -> 196875 | M8: 400 | N8: =ROUND(IF(L8*12<=600000, 0,IF(L8*12<=1200000, (L8*12-600000)*0.05,IF(L8*12<=2400000, 30000+(L8*12-1200000)*0.15,IF(L8*12<=3600000, 210000+(L8*12-2400000)*0.25,510000+(L8*12-3600000)*0.3))))/12, 0) -> 17031 | O8: =L8-M8-N8 -> 179444
A9: 1004 | B9: Zainab Bibi | C9: 55000 | D9: 160 | E9: 144 | F9: 2 | G9: =IF(F9=0,0,(C9/D9)*8*F9) -> 5500 | H9: 0 | I9: =C9/D9*1.5 -> 515.625 | J9: =H9*I9 -> 0 | K9: 10000 | L9: =(C9-G9)+J9+K9 -> 59500 | M9: 400 | N9: =ROUND(IF(L9*12<=600000, 0,IF(L9*12<=1200000, (L9*12-600000)*0.05,IF(L9*12<=2400000, 30000+(L9*12-1200000)*0.15,IF(L9*12<=3600000, 210000+(L9*12-2400000)*0.25,510000+(L9*12-3600000)*0.3))))/12, 0) -> 475 | O9: =L9-M9-N9 -> 58625
A10: 1005 | B10: Hamza Malik | C10: 110000 | D10: 160 | E10: 160 | F10: 0 | G10: =IF(F10=0,0,(C10/D10)*8*F10) -> 0 | H10: 10 | I10: =C10/D10*1.5 -> 1031.25 | J10: =H10*I10 -> 10312.5 | K10: 20000 | L10: =(C10-G10)+J10+K10 -> 140312.5 | M10: 400 | N10: =ROUND(IF(L10*12<=600000, 0,IF(L10*12<=1200000, (L10*12-600000)*0.05,IF(L10*12<=2400000, 30000+(L10*12-1200000)*0.15,IF(L10*12<=3600000, 210000+(L10*12-2400000)*0.25,510000+(L10*12-3600000)*0.3))))/12, 0) -> 8547 | O10: =L10-M10-N10 -> 131365.5
A11: 1006 | B11: Maryam Noor | C11: 75000 | D11: 160 | E11: 152 | F11: 1 | G11: =IF(F11=0,0,(C11/D11)*8*F11) -> 3750 | H11: 5 | I11: =C11/D11*1.5 -> 703.125 | J11: =H11*I11 -> 3515.625 | K11: 15000 | L11: =(C11-G11)+J11+K11 -> 89765.625 | M11: 400 | N11: =ROUND(IF(L11*12<=600000, 0,IF(L11*12<=1200000, (L11*12-600000)*0.05,IF(L11*12<=2400000, 30000+(L11*12-1200000)*0.15,IF(L11*12<=3600000, 210000+(L11*12-2400000)*0.25,510000+(L11*12-3600000)*0.3))))/12, 0) -> 1988 | O11: =L11-M11-N11 -> 87377.625
A12: 1007 | B12: Usman Ghani | C12: 185000 | D12: 160 | E12: 160 | F12: 0 | G12: =IF(F12=0,0,(C12/D12)*8*F12) -> 0 | H12: 0 | I12: =C12/D12*1.5 -> 1734.375 | J12: =H12*I12 -> 0 | K12: 35000 | L12: =(C12-G12)+J12+K12 -> 220000 | M12: 400 | N12: =ROUND(IF(L12*12<=600000, 0,IF(L12*12<=1200000, (L12*12-600000)*0.05,IF(L12*12<=2400000, 30000+(L12*12-1200000)*0.15,IF(L12*12<=3600000, 210000+(L12*12-2400000)*0.25,510000+(L12*12-3600000)*0.3))))/12, 0) -> 22500 | O12: =L12-M12-N12 -> 197100
A13: 1008 | B13: Fatima Ali | C13: 95000 | D13: 160 | E13: 160 | F13: 0 | G13: =IF(F13=0,0,(C13/D13)*8*F13) -> 0 | H13: 15 | I13: =C13/D13*1.5 -> 890.625 | J13: =H13*I13 -> 13359.375 | K13: 18000 | L13: =(C13-G13)+J13+K13 -> 126359.38 | M13: 400 | N13: =ROUND(IF(L13*12<=600000, 0,IF(L13*12<=1200000, (L13*12-600000)*0.05,IF(L13*12<=2400000, 30000+(L13*12-1200000)*0.15,IF(L13*12<=3600000, 210000+(L13*12-2400000)*0.25,510000+(L13*12-3600000)*0.3))))/12, 0) -> 6454 | O13: =L13-M13-N13 -> 119505.38
A14: 1009 | B14: Raza Abbas | C14: 40000 | D14: 160 | E14: 160 | F14: 0 | G14: =IF(F14=0,0,(C14/D14)*8*F14) -> 0 | H14: 20 | I14: =C14/D14*1.5 -> 375 | J14: =H14*I14 -> 7500 | K14: 5000 | L14: =(C14-G14)+J14+K14 -> 52500 | M14: 400 | N14: =ROUND(IF(L14*12<=600000, 0,IF(L14*12<=1200000, (L14*12-600000)*0.05,IF(L14*12<=2400000, 30000+(L14*12-1200000)*0.15,IF(L14*12<=3600000, 210000+(L14*12-2400000)*0.25,510000+(L14*12-3600000)*0.3))))/12, 0) -> 125 | O14: =L14-M14-N14 -> 51975
A15: 1010 | B15: Sana Javed | C15: 210000 | D15: 160 | E15: 136 | F15: 3 | G15: =IF(F15=0,0,(C15/D15)*8*F15) -> 31500 | H15: 0 | I15: =C15/D15*1.5 -> 1968.75 | J15: =H15*I15 -> 0 | K15: 40000 | L15: =(C15-G15)+J15+K15 -> 218500 | M15: 400 | N15: =ROUND(IF(L15*12<=600000, 0,IF(L15*12<=1200000, (L15*12-600000)*0.05,IF(L15*12<=2400000, 30000+(L15*12-1200000)*0.15,IF(L15*12<=3600000, 210000+(L15*12-2400000)*0.25,510000+(L15*12-3600000)*0.3))))/12, 0) -> 22125 | O15: =L15-M15-N15 -> 195975
A16: 1011 | B16: Kamran Akmal | C16: 130000 | D16: 160 | E16: 160 | F16: 0 | G16: =IF(F16=0,0,(C16/D16)*8*F16) -> 0 | H16: 6 | I16: =C16/D16*1.5 -> 1218.75 | J16: =H16*I16 -> 7312.5 | K16: 25000 | L16: =(C16-G16)+J16+K16 -> 162312.5 | M16: 400 | N16: =ROUND(IF(L16*12<=600000, 0,IF(L16*12<=1200000, (L16*12-600000)*0.05,IF(L16*12<=2400000, 30000+(L16*12-1200000)*0.15,IF(L16*12<=3600000, 210000+(L16*12-2400000)*0.25,510000+(L16*12-3600000)*0.3))))/12, 0) -> 11847 | O16: =L16-M16-N16 -> 150065.5
A17: 1012 | B17: Hina Rabbani | C17: 65000 | D17: 160 | E17: 152 | F17: 1 | G17: =IF(F17=0,0,(C17/D17)*8*F17) -> 3250 | H17: 0 | I17: =C17/D17*1.5 -> 609.375 | J17: =H17*I17 -> 0 | K17: 12000 | L17: =(C17-G17)+J17+K17 -> 73750 | M17: 400 | N17: =ROUND(IF(L17*12<=600000, 0,IF(L17*12<=1200000, (L17*12-600000)*0.05,IF(L17*12<=2400000, 30000+(L17*12-1200000)*0.15,IF(L17*12<=3600000, 210000+(L17*12-2400000)*0.25,510000+(L17*12-3600000)*0.3))))/12, 0) -> 1188 | O17: =L17-M17-N17 -> 72162
... A20: 1015 | B20: Asif Ali | C20: 45000 | D20: 160 | E20: 144 | F20: 2 | G20: =IF(F20=0,0,(C20/D20)*8*F20) -> 4500 | H20: 10 | I20: =C20/D20*1.5 -> 421.875 | J20: =H20*I20 -> 4218.75 | K20: 8000 | L20: =(C20-G20)+J20+K20 -> 52718.75 | M20: 400 | N20: =ROUND(IF(L20*12<=600000, 0,IF(L20*12<=1200000, (L20*12-600000)*0.05,IF(L20*12<=2400000, 30000+(L20*12-1200000)*0.15,IF(L20*12<=3600000, 210000+(L20*12-2400000)*0.25,510000+(L20*12-3600000)*0.3))))/12, 0) -> 136 | O20: =L20-M20-N20 -> 52182.75
A21: TOTAL | C21: =SUM(C6:C20) -> 1905000 | G21: =SUM(G6:G20) -> 61000 | J21: =SUM(J6:J20) -> 72843.75 | K21: =SUM(K6:K20) -> 361000 | L21: =SUM(L6:L20) -> 2277843.8 | M21: =SUM(M6:M20) -> 6000 | N21: =SUM(N6:N20) -> 205953 | O21: =SUM(O6:O20) -> 2065890.8

Sheet Summary Dashboard
A1: PAYROLL SUMMARY DASHBOARD|VELOCE DYNAMIC Pvt Ltd
A2: Month: June 2025
A4: Total Employees | D4: =COUNTA('Payroll Register'!B6:B20) -> 15
A7: Total Basic Salary | D7: ='Payroll Register'!C21 -> 1905000
A10: Total Gross Salary | D10: ='Payroll Register'!L21 -> 2277843.8
A13: Total Deductions | D13: ='Payroll Register'!M21+'Payroll Register'!N21 -> 211953
A16: Total Net Payable | D16: ='Payroll Register'!O21 -> 2065890.8
A19: Total OT Pay | D19: ='Payroll Register'!J21 -> 72843.75
A22: Total Allowances | D22: ='Payroll Register'!K21 -> 361000
A25: Total Tax Collected | D25: ='Payroll Register'!N21 -> 205953
A32: INCOME TAX SLABS — Pakistan FBR 2024-25
A33: Annual Income (PKR) | C33: Tax Rate | E33: Tax Formula
A34: Up to 600,000 | C34: 0% | E34: No Tax
A35: 600,001 – 1,200,000 | C35: 5% | E35: 5% of excess over 600K
A36: 1,200,001 – 2,400,000 | C36: 15% | E36: 30,000 + 15% of excess over 1.2M
A37: 2,400,001 – 3,600,000 | C37: 25% | E37: 210,000 + 25% of excess over 2.4M
A38: Above 3,600,000 | C38: 30% | E38: 510,000 + 30% of excess over 3.6M

Sheet Formula Legend
A1: PAYROLL FORMULA REFERENCE GUIDE
A2: Component | B2: Excel Formula Logic | C2: Why Used
A3: Absent Deduction | B3: (Basic / Total Hrs) × 8 × Absent Days | C3: Daily rate per hour × 8hr day × absents
A4: OT Rate (1.5x) | B4: Basic / Total Hrs × 1.5 | C4: Overtime premium = 1.5× regular hourly rate
A5: OT Pay | B5: OT Hours × OT Rate | C5: Total overtime earned
A6: Gross Salary | B6: (Basic − Absent Deduction) + OT Pay + Allowances | C6: Total earnings before deductions
A7: EOBI | B7: Fixed PKR 400 | C7: Government-mandated social security
A8: Income Tax | B8: Pakistan FBR slabs (annual basis ÷ 12) | C8: Progressive tax on annual gross income
A9: Net Pay | B9: Gross − EOBI − Income Tax | C9: Actual bank transfer amount
